qrDocumentIndexer/__init__.py
qrDocumentIndexer/__main__.py
qrDocumentIndexer/page_info.py
qrDocumentIndexer/pdf_ingest.py
qrDocumentIndexer/pdf_sorting.py
qrDocumentIndexer/reconstituted_document.py
qrDocumentIndexer/scanned_documents.py
qrDocumentIndexer/scanned_page.py
qrDocumentIndexer/gui/__init__.py
qrDocumentIndexer/gui/launch_window.py
qrDocumentIndexer/gui/sort_actions_handler.py
qrDocumentIndexer/gui/sort_options_frame.py
qrDocumentIndexer/gui/stamp_action_handler.py
qrDocumentIndexer/gui/stamp_options_frame.py
qrDocumentIndexer/gui/file_select/__init__.py
qrDocumentIndexer/gui/file_select/action_handler.py
qrDocumentIndexer/gui/file_select/file_list.py
qrDocumentIndexer/gui/file_select/file_select_window.py
qrDocumentIndexer/gui/file_select/options_frame.py
qrDocumentIndexer-0.1.0.dist-info/LICENSE
qrDocumentIndexer-0.1.0.dist-info/METADATA
qrDocumentIndexer-0.1.0.dist-info/WHEEL
qrDocumentIndexer-0.1.0.dist-info/top_level.txt
qrDocumentIndexer-0.1.0.dist-info/RECORD
