Metadata-Version: 2.1
Name: qrDocumentIndexer
Version: 0.1.0
Summary: Tool for indexing and sorting documents using QR codes
Author-email: Jonathan Pecar <jonathan.pecar@gmail.com>
License: GNU AFFERO GENERAL PUBLIC LICENSE
Project-URL: Homepage, https://github.com/jonpecar/qrDocumentIndexer
Keywords: sorter,qrcode,docmentsorter
Classifier: License :: OSI Approved :: GNU Affero General Public License v3
Classifier: Programming Language :: Python
Classifier: Programming Language :: Python :: 3
Requires-Python: >=3.10
License-File: LICENSE
Requires-Dist: PyMuPDF
Requires-Dist: Pillow
Requires-Dist: qrcode
Requires-Dist: tqdm
Requires-Dist: qreader
Requires-Dist: termcolor
Requires-Dist: typing-extensions
Requires-Dist: customtkinter
Requires-Dist: CTkMessageBox
Provides-Extra: dev
Requires-Dist: pytest ; extra == 'dev'
Requires-Dist: bumpver ; extra == 'dev'
Requires-Dist: setuptools ; extra == 'dev'
